rainbows/__init__.py
rainbows/_base_client.py
rainbows/_client.py
rainbows/_compat.py
rainbows/_constants.py
rainbows/_exceptions.py
rainbows/_files.py
rainbows/_models.py
rainbows/_qs.py
rainbows/_resource.py
rainbows/_response.py
rainbows/_streaming.py
rainbows/_types.py
rainbows/_version.py
rainbows/py.typed
rainbows/_utils/__init__.py
rainbows/_utils/_compat.py
rainbows/_utils/_datetime_parse.py
rainbows/_utils/_logs.py
rainbows/_utils/_proxy.py
rainbows/_utils/_reflection.py
rainbows/_utils/_resources_proxy.py
rainbows/_utils/_streams.py
rainbows/_utils/_sync.py
rainbows/_utils/_transform.py
rainbows/_utils/_typing.py
rainbows/_utils/_utils.py
rainbows/lib/.keep
rainbows/resources/__init__.py
rainbows/resources/jobs.py
rainbows/types/__init__.py
rainbows/types/job_get_params.py
rainbows/types/job_get_response.py
rainbows/types/job_retrieve_term_based_params.py
rainbows/types/job_retrieve_term_based_response.py
rainbows/types/job_upsert_from_jsonl_params.py
rainbows/types/job_upsert_from_jsonl_response.py
rainbows/types/job_upsert_params.py
rainbows/types/job_upsert_response.py
rainbows-6.1.0.dist-info/METADATA
rainbows-6.1.0.dist-info/WHEEL
rainbows-6.1.0.dist-info/licenses/LICENSE
rainbows-6.1.0.dist-info/RECORD
